vibe_ukis/documentation/chainlit.md
vibe_ukis/documentation/firecrawl.md
vibe_ukis/documentation/llamaindex.md
vibe_ukis/documentation/qdrant.md
vibe_ukis/logo.py
vibe_ukis/main.py
vibe_ukis/start/__init__.py
vibe_ukis/start/antigravity.py
vibe_ukis/start/cursor.py
vibe_ukis/start/data.py
vibe_ukis/start/mcp.py
vibe_ukis/start/mcp_terminal.py
vibe_ukis/start/mcp_tools.py
vibe_ukis/start/skills.py
vibe_ukis/start/terminal.py
vibe_ukis/start/utils.py
vibe_ukis/start/windsurf.py
vibe_ukis-1.0.2.dist-info/METADATA
vibe_ukis-1.0.2.dist-info/WHEEL
vibe_ukis-1.0.2.dist-info/entry_points.txt
vibe_ukis-1.0.2.dist-info/licenses/LICENSE
vibe_ukis-1.0.2.dist-info/RECORD
