Metadata-Version: 2.4
Name: vibe-ukis
Version: 1.0.2
Summary: vibe-ukis is a set of tools that are designed to help developers build working and reliable applications with LlamaIndex, llama-index-workflows and Chainlit.
License-File: LICENSE
Requires-Python: >=3.10
Requires-Dist: fastmcp>=2.11.3
Requires-Dist: html2text>=2024.2.26
Requires-Dist: httpx>=0.28.1
Requires-Dist: prompt-toolkit>=3.0.51
Requires-Dist: rich-gradient>=0.3.3
Requires-Dist: rich>=14.1.0
